riptide_engine_docker/__init__.py
riptide_engine_docker/assets.py
riptide_engine_docker/cmd_detached.py
riptide_engine_docker/container_builder.py
riptide_engine_docker/engine.py
riptide_engine_docker/fg.py
riptide_engine_docker/named_volumes.py
riptide_engine_docker/network.py
riptide_engine_docker/path_utils.py
riptide_engine_docker/service.py
riptide_engine_docker/assets/entrypoint.sh
riptide_engine_docker/tests/__init__.py
riptide_engine_docker/tests/integration/__init__.py
riptide_engine_docker/tests/integration/tester.py
riptide_engine_docker/tests/unit/container_builder_test.py
riptide_engine_docker-0.9.2.dist-info/licenses/LICENSE
riptide_engine_docker-0.9.2.dist-info/METADATA
riptide_engine_docker-0.9.2.dist-info/WHEEL
riptide_engine_docker-0.9.2.dist-info/entry_points.txt
riptide_engine_docker-0.9.2.dist-info/top_level.txt
riptide_engine_docker-0.9.2.dist-info/RECORD
